price_pred/__init__.py
price_pred/feature_selection.py
price_pred/pipelines.py
price_pred/transformers.py
price_pred/validation.py
price_predictions-1.1.0.dist-info/METADATA
price_predictions-1.1.0.dist-info/WHEEL
price_predictions-1.1.0.dist-info/top_level.txt
price_predictions-1.1.0.dist-info/RECORD
